[{"ability":"每个夜晚，如果死亡的玩家数量大于存活的玩家数量，你会得知一个存活的角色。恶魔知道你是国王。","image":"https://oss.gstonegames.com/data_file/clocktower/role_icon/king.png","edition":"custom","flavor":"","id":"king_gstone","firstNightReminder":"唤醒恶魔，并告诉他国王是谁。","otherNightReminder":"如果死亡玩家人数大于存活玩家，唤醒国王并对其展示一个存活的角色标记。","name":"国王","otherNight":131,"setup":0,"reminders":[],"remindersGlobal":[],"team":"townsfolk","firstNight":31,"GstoneID":"king"},{"ability":"如果恶魔杀死了国王，你会得知哪名玩家是恶魔。[+国王]","image":"https://oss.gstonegames.com/data_file/clocktower/role_icon/choirboy.png","edition":"custom","flavor":"","id":"choirboy_gstone","firstNightReminder":"","otherNightReminder":"如果国王被恶魔杀死，将唱诗男孩唤醒并告诉他谁是那个杀死国王的恶魔。","name":"唱诗男孩","otherNight":102,"setup":1,"reminders":[],"remindersGlobal":[],"team":"townsfolk","firstNight":0,"GstoneID":"choirboy"},{"ability":"在你的首个夜晚，你会得知一名善良玩家和他的角色。如果恶魔杀死了他，你也会死亡。","image":"https://oss.gstonegames.com/data_file/clocktower/role_icon/grandmother.png","edition":"custom","flavor":"","id":"grandmother_gstone","firstNightReminder":"指向她的孙子玩家，并展示该玩家的角色标记。","otherNightReminder":"如果孙子被恶魔杀死，祖母也会一同死亡。标记祖母死亡。","name":"祖母","otherNight":95,"setup":0,"reminders":["孙子","死亡"],"remindersGlobal":[],"team":"townsfolk","firstNight":83,"GstoneID":"grandmother"},{"ability":"每个夜晚，你要选择一个镇民角色：他的能力会产生错误信息，直到下个黄昏。","image":"https://oss.gstonegames.com/data_file/clocktower/upload/202301/c_6984587694761_17384eb3.jpg","edition":"custom","flavor":"","id":"xionghaizi_gstone","firstNightReminder":"唤醒熊孩子，让其选择一个镇民角色。如果该角色在场，在对应角色标记旁放置“捣蛋”提示标记。","otherNightReminder":"移除上个夜晚放置的“捣蛋”提示标记。唤醒熊孩子，让其选择一个镇民角色。如果该角色在场，在对应角色标记旁放置“捣蛋”提示标记。","name":"熊孩子","otherNight":25,"setup":0,"reminders":["捣蛋"],"remindersGlobal":[],"team":"townsfolk","firstNight":72,"GstoneID":"xionghaizi"},{"ability":"每局游戏限一次，在夜晚时，你可以选择一名存活的玩家：如果你选中了落难少女，她会变成一个不在场的镇民角色。[+落难少女]","image":"https://oss.gstonegames.com/data_file/clocktower/role_icon/huntsman.png","edition":"custom","flavor":"","id":"huntsman_gstone","firstNightReminder":"巡山人选择不使用能力，或指向一名玩家。如果他指向了落难少女，则为落难少女安排一个新的不在场镇民角色，将其唤醒并告知她新的角色。","otherNightReminder":"巡山人选择不使用能力，或指向一名玩家。如果他指向了落难少女，则为落难少女安排一个新的不在场镇民角色，将其唤醒并告知她新的角色。","name":"巡山人","otherNight":109,"setup":1,"reminders":["失去能力"],"remindersGlobal":[],"team":"townsfolk","firstNight":74,"GstoneID":"huntsman"},{"ability":"在你的首个夜晚，你会得知两名善良玩家。他们之中会有一人醉酒，即使你已死亡。","image":"https://oss.gstonegames.com/data_file/clocktower/upload/202301/c_8586487694761_0ecde168.jpg","edition":"custom","flavor":"","id":"dianxiaoer_gstone","firstNightReminder":"唤醒店小二，对他指向标记有店小二的“熟客”和“醉酒”提示标记的这两名玩家。","otherNightReminder":"","name":"店小二","otherNight":0,"setup":0,"reminders":["熟客","醉酒"],"remindersGlobal":[],"team":"townsfolk","firstNight":94,"GstoneID":"dianxiaoer"},{"ability":"每个夜晚，你要选择除你以外的两名存活的玩家：你会得知他们中有几人在当晚因其自身能力而被唤醒。","image":"https://oss.gstonegames.com/data_file/clocktower/role_icon/chambermaid.png","edition":"custom","flavor":"","id":"chambermaid_gstone","firstNightReminder":"让侍女选择除自己外的两名存活玩家。给她展示数字手势来告诉她这些玩家中有几人因自身能力被唤醒。","otherNightReminder":"让侍女选择除自己外的两名存活玩家。给她展示数字手势来告诉她这些玩家中有几人因自身能力被唤醒。","name":"侍女","otherNight":148,"setup":0,"reminders":[],"remindersGlobal":[],"team":"townsfolk","firstNight":124,"GstoneID":"chambermaid"},{"ability":"每局游戏限一次，在夜晚时，你可以选择让恶魔变成你选择的恶魔角色，或让所有爪牙变成你选择的爪牙角色。","image":"https://oss.gstonegames.com/data_file/clocktower/role_icon/engineer.png","edition":"custom","flavor":"","id":"engineer_gstone","firstNightReminder":"工程师选择不使用能力，或在剧本列表中选择恶魔或爪牙角色。如果他选择爪牙角色，则需要选择对应数量的爪牙。然后将这些玩家依次唤醒，并告知他们变成了什么角色。","otherNightReminder":"工程师选择不使用能力，或在剧本列表中选择恶魔或爪牙角色。如果他选择爪牙角色，则需要选择对应数量的爪牙。然后将这些玩家依次唤醒，并告知他们变成了什么角色。","name":"工程师","otherNight":11,"setup":0,"reminders":["失去能力"],"remindersGlobal":[],"team":"townsfolk","firstNight":41,"GstoneID":"engineer"},{"ability":"每局游戏限一次，在夜晚时*，你可以选择一名死亡的玩家：如果他是镇民，你会将他起死回生。","image":"https://oss.gstonegames.com/data_file/clocktower/role_icon/professor.png","edition":"custom","flavor":"","id":"professor_gstone","firstNightReminder":"","otherNightReminder":"教授可以选择一名死亡玩家。如果他这么做了，标记教授失去能力，然后如果那名玩家是镇民，标记那名玩家被复活。之后的夜晚无需再唤醒教授。","name":"教授","otherNight":105,"setup":0,"reminders":["复活","失去能力"],"remindersGlobal":[],"team":"townsfolk","firstNight":0,"GstoneID":"professor"},{"ability":"每个白天，你可以私下询问说书人以得知两条信息：一个是正确的，一个是错误的。","image":"https://oss.gstonegames.com/data_file/clocktower/role_icon/savant.png","edition":"custom","flavor":"","id":"savant_gstone","firstNightReminder":"","otherNightReminder":"","name":"博学者","otherNight":0,"setup":0,"reminders":[],"remindersGlobal":[],"team":"townsfolk","firstNight":0,"GstoneID":"savant"},{"ability":"每个夜晚，你会得知一名不同角色类型的玩家，直到场上所有的角色类型你都得知过一次。[+1 外来者]","image":"https://oss.gstonegames.com/data_file/clocktower/role_icon/balloonist.png","edition":"custom","flavor":"","id":"balloonist_gstone","firstNightReminder":"选择一种角色类型，并告知其一个符合该类型的玩家。在该玩家旁边标记已被知晓。","otherNightReminder":"选择一种尚未被气球驾驶员知晓的角色类型，并告知其一个符合该类型的玩家。在该玩家旁边标记已被知晓。如果所有类型均已被知晓或无该种类型，气球驾驶员不会醒来。","name":"气球驾驶员","otherNight":121,"setup":1,"reminders":["得知镇民","得知外来者","得知爪牙","得知恶魔"],"remindersGlobal":[],"team":"townsfolk","firstNight":91,"GstoneID":"balloonist"},{"ability":"在你的首个夜晚，你会得知三名玩家：其中有且只有一名玩家是邪恶的。","image":"https://oss.gstonegames.com/data_file/clocktower/role_icon/noble.png","edition":"custom","flavor":"","id":"noble_gstone","firstNightReminder":"以任意顺序指向三名玩家，其中一名邪恶。","otherNightReminder":"","name":"贵族","otherNight":0,"setup":0,"reminders":["得知"],"remindersGlobal":[],"team":"townsfolk","firstNight":89,"GstoneID":"noble"},{"ability":"在你的首个夜晚，你会得知两个善良角色和两个邪恶角色。其中有且只有两个角色在场。","image":"https://oss.gstonegames.com/data_file/clocktower/upload/202301/c_4630967694761_bd56d041.jpg","edition":"custom","flavor":"","id":"yinyangshi_gstone","firstNightReminder":"唤醒阴阳师，并对其展示两个善良角色，两个邪恶角色，共四个角色标记。其中正好只有两个角色在场。","otherNightReminder":"","name":"阴阳师","otherNight":0,"setup":0,"reminders":[],"remindersGlobal":[],"team":"townsfolk","firstNight":92,"GstoneID":"yinyangshi"},{"ability":"所有爪牙都知道落难少女在场。每局游戏限一次，任意爪牙可以公开猜测你是落难少女，如果猜对，你的阵营落败。","image":"https://oss.gstonegames.com/data_file/clocktower/role_icon/damsel.png","edition":"custom","flavor":"","id":"damsel_gstone","firstNightReminder":"唤醒所有爪牙，并告知他们场中有落难少女。","otherNightReminder":"如果被巡山人选中，唤醒并为其展示新角色。","name":"落难少女","otherNight":52,"setup":0,"reminders":["已被猜测"],"remindersGlobal":[],"team":"outsider","firstNight":7,"GstoneID":"damsel"},{"ability":"如果你死亡，当晚爪牙和恶魔玩家可以选择变成新的爪牙和恶魔角色。","image":"https://oss.gstonegames.com/data_file/clocktower/upload/202312/c_9723021341071_86da6df4.jpg","edition":"custom","flavor":"","id":"hatter_gstone","firstNightReminder":"","otherNightReminder":"在当晚，一同唤醒所有爪牙和恶魔。对他们展示“该角色的能力对你生效”信息标记，然后展示帽匠角色标记。每名以此被唤醒的玩家可以选择摇头或指向角色列表上与自己当前角色类型相同的一个角色。如果一名玩家在做出自己的选择后会使得自己的角色与一名其他玩家选择的角色相同，对他摇头示意他重新选择。在选择完成后让他重新入睡。移除“今晚茶会”提示标记。根据这些玩家的选择，在魔典上执行相应的角色变化操作。","name":"帽匠","otherNight":8,"setup":0,"reminders":["今晚茶会"],"remindersGlobal":[],"team":"outsider","firstNight":0,"GstoneID":"hatter"},{"ability":"如果你死亡，在当晚恶魔可以选择两名玩家（不能选择其他恶魔）交换角色。","image":"https://oss.gstonegames.com/data_file/clocktower/role_icon/barber.png","edition":"custom","flavor":"","id":"barber_gstone","firstNightReminder":"","otherNightReminder":"如果理发师今天死亡了，唤醒恶魔并展示“该角色的效果对你生效”信息标记和理发师角色标记。如果恶魔选择了两名玩家，将这两名玩家分别独自唤醒。对他们展示“你是”信息标记和他们的新角色标记。","name":"理发师","otherNight":96,"setup":0,"reminders":["今晚理发"],"remindersGlobal":[],"team":"outsider","firstNight":0,"GstoneID":"barber"},{"ability":"恶魔知道你在场。每局游戏限一次，恶魔可以拜访说书人并猜测谁是书生。如果恶魔猜测正确，即使你已死亡，当晚该恶魔可以选择一名玩家：他死亡。","image":"https://oss.gstonegames.com/data_file/clocktower/upload/202310/c_9486455308961_c35f60ab.jpg","edition":"custom","flavor":"","id":"shusheng_gstone","firstNightReminder":"唤醒恶魔，并对他展示“该角色的能力对你触发”提示标记与书生角色标记。","otherNightReminder":"如果白天恶魔成功猜中了书生是谁，唤醒那个恶魔，让其选择一名玩家。标记那名玩家死亡。","name":"书生","otherNight":85,"setup":0,"reminders":["已猜测","猜测正确","死亡"],"remindersGlobal":[],"team":"outsider","firstNight":33,"GstoneID":"shusheng"},{"ability":"所有玩家在投票时闭眼，且票数会秘密统计。对你的提名只在你投票时才会统计票数。","image":"https://oss.gstonegames.com/data_file/clocktower/upload/202303/c_1527286859761_46867343.jpg","edition":"custom","flavor":"","id":"organ_grinder_gstone","firstNightReminder":"","otherNightReminder":"","name":"街头风琴手","otherNight":0,"setup":0,"reminders":["即将被处决"],"remindersGlobal":[],"team":"minion","firstNight":0,"GstoneID":"organ_grinder"},{"ability":"所有玩家都知道你是维齐尔。你在白天时不会死亡。如果一次提名中有善良玩家投票，你可以让被提名者立即被处决。","image":"https://oss.gstonegames.com/data_file/clocktower/upload/202304/c_8651385151861_48d3dd5d.jpg","edition":"custom","flavor":"","id":"vizier_gstone","firstNightReminder":"告诉所有玩家维齐尔在场，并指向维齐尔玩家。","otherNightReminder":"","name":"维齐尔","otherNight":0,"setup":0,"reminders":[],"remindersGlobal":[],"team":"minion","firstNight":129,"GstoneID":"vizier"},{"ability":"你与一名对立阵营的玩家互相知道对方是什么角色。如果其中善良玩家被处决，邪恶阵营获胜。如果你们都存活，善良阵营无法获胜。","image":"https://oss.gstonegames.com/data_file/clocktower/role_icon/evil_twin.png","edition":"custom","flavor":"","id":"evil_twin_gstone","firstNightReminder":"唤醒镜像双子和他的对立双子，让他们进行眼神接触。对镜像双子展示对立双子的角色标记，并对对立双子展示镜像双子的角色标记。","otherNightReminder":"","name":"镜像双子","otherNight":0,"setup":0,"reminders":["对立双子"],"remindersGlobal":[],"team":"minion","firstNight":56,"GstoneID":"evil_twin"},{"ability":"如果大于等于五名玩家存活时（旅行者不计算在内）恶魔死亡，你变成那个恶魔。","image":"https://oss.gstonegames.com/data_file/clocktower/role_icon/scarlet_woman.png","edition":"custom","flavor":"","id":"scarlet_woman_gstone","firstNightReminder":"","otherNightReminder":"如果红唇女郎今天变成了小恶魔，对她展示“你是”信息标记，和小恶魔角色标记。","name":"红唇女郎","otherNight":37,"setup":0,"reminders":[],"remindersGlobal":["是恶魔"],"team":"minion","firstNight":0,"GstoneID":"scarlet_woman"},{"ability":"在你的首个夜晚，你要选择一名玩家：他会知道狐媚娘在场。如果你死于处决，当晚他转变为邪恶阵营。","image":"https://oss.gstonegames.com/data_file/clocktower/upload/202310/c_4772055308961_7bc92354.jpg","edition":"custom","flavor":"","id":"humeiniang_gstone","firstNightReminder":"唤醒狐媚娘，让她选择一名玩家。标记那名玩家“被魅惑”。随后唤醒那名玩家，对他展示“该角色的能力对你触发”和狐媚娘角色标记。","otherNightReminder":"如果今日狐媚娘死于处决，且被魅惑的玩家为善良阵营，唤醒被魅惑的玩家，对他展示“你是”和朝下的大拇指。","name":"狐媚娘","otherNight":33,"setup":0,"reminders":["被魅惑"],"remindersGlobal":[],"team":"minion","firstNight":62,"GstoneID":"humeiniang"},{"ability":"每个夜晚*，你要选择任意数量的非旅行者玩家或一名旅行者玩家：如果他们的角色类型均不相同，他们死亡。[+1外来者]","image":"https://oss.gstonegames.com/data_file/clocktower/upload/202301/c_5897997694761_fbe1f00c.jpg","edition":"custom","flavor":"","id":"taotie_gstone","firstNightReminder":"","otherNightReminder":"唤醒饕餮，让其选择任意数量的玩家。如果这些玩家的角色类型均不相同，标记这些玩家死亡。","name":"饕餮","otherNight":81,"setup":1,"reminders":["死亡"],"remindersGlobal":[],"team":"demon","firstNight":0,"GstoneID":"taotie"},{"ability":"每个夜晚*，你要选择两名玩家：他们死亡。你的上个夜晚选择过的且当前死亡的玩家可能会被你反刍。","image":"https://oss.gstonegames.com/data_file/clocktower/role_icon/shabaloth.png","edition":"custom","flavor":"","id":"shabaloth_gstone","firstNightReminder":"","otherNightReminder":"上一夜被沙巴洛斯选择且当前已死亡的玩家之一可能被反刍，如果被反刍，标记那名玩家被复活。让沙巴洛斯选择两名玩家。标记这两名玩家死亡。","name":"沙巴洛斯","otherNight":52,"setup":0,"reminders":["死亡","复活"],"remindersGlobal":[],"team":"demon","firstNight":0,"GstoneID":"shabaloth"},{"ability":"每个夜晚*，你要选择一个角色：他死亡。如果该角色不在场，则由说书人来决定谁会被你杀死。","image":"https://oss.gstonegames.com/data_file/clocktower/upload/202310/c_6886084308961_f221dd48.jpg","edition":"custom","flavor":"","id":"ojo_gstone","firstNightReminder":"","otherNightReminder":"唤醒奥赫。让奥赫指向角色列表上的一个角色标记。如果被选择的角色在场，对应的玩家死亡——使用“死亡”提示标记标记那名玩家。如果被选择的角色不在场，那么改为你来选择任意一名玩家，那名玩家死亡——使用“死亡”提示标记标记那名玩家。让奥赫重新入睡。","name":"奥赫","otherNight":62,"setup":0,"reminders":["死亡"],"remindersGlobal":[],"team":"demon","firstNight":0,"GstoneID":"ojo"}]